LICENSE
MANIFEST.in
README.md
pyproject.toml
setup.cfg
setup.py
django_permagate.egg-info/PKG-INFO
django_permagate.egg-info/SOURCES.txt
django_permagate.egg-info/dependency_links.txt
django_permagate.egg-info/requires.txt
django_permagate.egg-info/top_level.txt
permagate/__init__.py
permagate/admin.py
permagate/apps.py
permagate/core.py
permagate/models.py
permagate/permission.py
permagate/test_permissions.py
permagate/tests.py
permagate/views.py
permagate/migrations/0001_initial.py
permagate/migrations/__init__.py